equake/__init__.py
equake/_requests.py
equake/_utils.py
equake/exceptions.py
equake/filt.py
equake/quake.py
equake-0.0.1.dist-info/LICENSE
equake-0.0.1.dist-info/METADATA
equake-0.0.1.dist-info/WHEEL
equake-0.0.1.dist-info/top_level.txt
equake-0.0.1.dist-info/RECORD
