Metadata-Version: 2.1
Name: equake
Version: 0.0.1
Summary: A library to intuitively access and handle earthquake data
Author-email: Leo Zhang <leozhang0214@gmail.com>
Project-URL: Homepage, https://github.com/leoz0214/equake
Project-URL: Bug Tracker, https://github.com/leoz0214/equake/issues
Classifier: Programming Language :: Python :: 3
Classifier: License :: OSI Approved :: MIT License
Classifier: Operating System :: OS Independent
Requires-Python: >=3.7
License-File: LICENSE
